symfc/__init__.py
symfc/api_symfc.py
symfc/version.py
symfc/basis_sets/__init__.py
symfc/basis_sets/basis_sets_O1.py
symfc/basis_sets/basis_sets_O2.py
symfc/basis_sets/basis_sets_O3.py
symfc/basis_sets/basis_sets_O4.py
symfc/basis_sets/basis_sets_base.py
symfc/solvers/__init__.py
symfc/solvers/solver_O2.py
symfc/solvers/solver_O2O3.py
symfc/solvers/solver_O2O3O4.py
symfc/solvers/solver_O3.py
symfc/solvers/solver_O3O4.py
symfc/solvers/solver_O4.py
symfc/solvers/solver_base.py
symfc/spg_reps/__init__.py
symfc/spg_reps/spg_reps_O1.py
symfc/spg_reps/spg_reps_O2.py
symfc/spg_reps/spg_reps_O3.py
symfc/spg_reps/spg_reps_O4.py
symfc/spg_reps/spg_reps_base.py
symfc/utils/__init__.py
symfc/utils/cutoff_tools.py
symfc/utils/eig_tools.py
symfc/utils/matrix.py
symfc/utils/permutation_tools.py
symfc/utils/permutation_tools_O2.py
symfc/utils/permutation_tools_O3.py
symfc/utils/permutation_tools_O4.py
symfc/utils/rotation_tools_O2.py
symfc/utils/solver_funcs.py
symfc/utils/translation_tools_O1.py
symfc/utils/translation_tools_O2.py
symfc/utils/translation_tools_O3.py
symfc/utils/translation_tools_O4.py
symfc/utils/utils.py
symfc/utils/utils_O1.py
symfc/utils/utils_O2.py
symfc/utils/utils_O3.py
symfc/utils/utils_O4.py
symfc/utils/rotation_dev/__init__.py
symfc/utils/rotation_dev/run_rotation_tools_O2.py
symfc/utils/rotation_dev/run_rotation_tools_O3.py
symfc/utils/rotation_dev/run_test_O2.py
symfc-1.5.3.dist-info/licenses/LICENSE
symfc-1.5.3.dist-info/METADATA
symfc-1.5.3.dist-info/WHEEL
symfc-1.5.3.dist-info/top_level.txt
symfc-1.5.3.dist-info/RECORD
