Metadata-Version: 2.4
Name: symfc
Version: 1.5.3
Summary: This is the symfc module.
Author-email: Atsuto Seko <seko@cms.mtl.kyoto-u.ac.jp>
Maintainer-email: Atsushi Togo <atztogo@gmail.com>
License: BSD 3-Clause License
Project-URL: Homepage, https://github.com/symfc/symfc
Requires-Python: >=3.9
License-File: LICENSE
Requires-Dist: numpy
Requires-Dist: scipy!=1.11.0,!=1.11.1,!=1.11.2
Requires-Dist: spglib
Dynamic: license-file
